main.py
mseep_fofa_mcp_server-0.1.1.dist-info/METADATA
mseep_fofa_mcp_server-0.1.1.dist-info/WHEEL
mseep_fofa_mcp_server-0.1.1.dist-info/entry_points.txt
mseep_fofa_mcp_server-0.1.1.dist-info/top_level.txt
mseep_fofa_mcp_server-0.1.1.dist-info/RECORD
