Metadata-Version: 2.4
Name: mseep-fofa-mcp-server
Version: 0.1.1
Summary: A server for querying FOFA API using MCP
Author-email: mseep <support@skydeck.ai>
Requires-Python: >=3.11
Requires-Dist: httpx>=0.28.1
Requires-Dist: mcp[cli]>=1.4.0
